odoo/addons/membership_delegated_partner_line/README.rst
odoo/addons/membership_delegated_partner_line/__init__.py
odoo/addons/membership_delegated_partner_line/__manifest__.py
odoo/addons/membership_delegated_partner_line/i18n/it.po
odoo/addons/membership_delegated_partner_line/i18n/membership_delegated_partner_line.pot
odoo/addons/membership_delegated_partner_line/models/__init__.py
odoo/addons/membership_delegated_partner_line/models/account_move.py
odoo/addons/membership_delegated_partner_line/models/account_move_line.py
odoo/addons/membership_delegated_partner_line/models/membership_line.py
odoo/addons/membership_delegated_partner_line/readme/CONFIGURE.rst
odoo/addons/membership_delegated_partner_line/readme/CONTRIBUTORS.rst
odoo/addons/membership_delegated_partner_line/readme/CREDITS.rst
odoo/addons/membership_delegated_partner_line/readme/DESCRIPTION.rst
odoo/addons/membership_delegated_partner_line/readme/USAGE.rst
odoo/addons/membership_delegated_partner_line/scripts/replace_membership_delegated_partner.sql
odoo/addons/membership_delegated_partner_line/static/description/icon.png
odoo/addons/membership_delegated_partner_line/static/description/index.html
odoo/addons/membership_delegated_partner_line/tests/__init__.py
odoo/addons/membership_delegated_partner_line/tests/test_membership_delegate.py
odoo/addons/membership_delegated_partner_line/views/account_move.xml
odoo14_addon_membership_delegated_partner_line-14.0.1.0.1.dev3.dist-info/METADATA
odoo14_addon_membership_delegated_partner_line-14.0.1.0.1.dev3.dist-info/WHEEL
odoo14_addon_membership_delegated_partner_line-14.0.1.0.1.dev3.dist-info/top_level.txt
odoo14_addon_membership_delegated_partner_line-14.0.1.0.1.dev3.dist-info/RECORD
