Metadata-Version: 2.1
Name: odoo14-addon-membership_delegated_partner_line
Version: 14.0.1.0.1.dev3
Summary: Adds ability to specify member at invoice line level
Home-page: https://github.com/OCA/vertical-association
Author: Graeme Gellatly,Odoo Community Association (OCA)
Author-email: support@odoo-community.org
License: AGPL-3
Classifier: Programming Language :: Python
Classifier: Framework :: Odoo
Classifier: Framework :: Odoo :: 14.0
Classifier: License :: OSI Approved :: GNU Affero General Public License v3
Requires-Python: >=3.6
Requires-Dist: odoo<14.1dev,>=14.0a
